django_schedules/__init__.py
django_schedules/conf.py
django_schedules/schedules.py
django_schedules/tests.py
django_schedules/utils.py
django_schedules/management/__init__.py
django_schedules/management/commands/__init__.py
django_schedules/management/commands/schedules_list.py
django_schedules/management/commands/schedules_run.py
django_schedules/management/commands/schedules_update_cron.py
django_schedules/management/commands/schedules_update_systemd.py
django_schedules-1.1.2.dist-info/METADATA
django_schedules-1.1.2.dist-info/WHEEL
django_schedules-1.1.2.dist-info/licenses/LICENSE
django_schedules-1.1.2.dist-info/RECORD
