Metadata-Version: 2.4
Name: django-schedules
Version: 1.1.2
Summary: A Django app to define routines that should run periodically
Project-URL: Homepage, https://gitlab.com/sedrubal/django-schedules/
Author-email: sedrubal <dev@sedrubal.de>
License: MIT
License-File: LICENSE
Requires-Python: <4,>=3.11
Requires-Dist: django-appconf<2,>=1.2
Requires-Dist: django>=4.2
Requires-Dist: tabulate<1,>=0.9
